odoo9_addon_base_cron_exclusion-9.0.1.0.0-py2.7-nspkg.pth
odoo9_addon_base_cron_exclusion-9.0.1.0.0.dist-info/DESCRIPTION.rst
odoo9_addon_base_cron_exclusion-9.0.1.0.0.dist-info/METADATA
odoo9_addon_base_cron_exclusion-9.0.1.0.0.dist-info/RECORD
odoo9_addon_base_cron_exclusion-9.0.1.0.0.dist-info/WHEEL
odoo9_addon_base_cron_exclusion-9.0.1.0.0.dist-info/metadata.json
odoo9_addon_base_cron_exclusion-9.0.1.0.0.dist-info/namespace_packages.txt
odoo9_addon_base_cron_exclusion-9.0.1.0.0.dist-info/top_level.txt
odoo_addons/base_cron_exclusion/README.rst
odoo_addons/base_cron_exclusion/__init__.py
odoo_addons/base_cron_exclusion/__openerp__.py
odoo_addons/base_cron_exclusion/models/__init__.py
odoo_addons/base_cron_exclusion/models/ir_cron.py
odoo_addons/base_cron_exclusion/views/ir_cron_view.xml
